tornado_shutdown/__about__.py
tornado_shutdown/__init__.py
tornado_shutdown/__main__.py
tornado_shutdown-1.1.0.dist-info/DESCRIPTION.rst
tornado_shutdown-1.1.0.dist-info/METADATA
tornado_shutdown-1.1.0.dist-info/RECORD
tornado_shutdown-1.1.0.dist-info/WHEEL
tornado_shutdown-1.1.0.dist-info/metadata.json
tornado_shutdown-1.1.0.dist-info/top_level.txt
