Metadata-Version: 2.0
Name: tornado-shutdown
Version: 1.1.0
Summary: Utility library to help graceful shutdown of Tornado processes.
Home-page: https://github.com/RealKinetic/tornado-shutdown
Author: Nick Joyce
Author-email: nick.joyce@realkinetic.com
License: UNKNOWN
Platform: UNKNOWN
Requires-Dist: tornado (>=3)
